{
  "recentFiles": [
    {
      "basename": "Lecture 22：图的遍历",
      "path": "03_专业/01_数据结构/6. 图/Lecture 22：图的遍历.md"
    },
    {
      "basename": "Lecture 20：图基本概念",
      "path": "03_专业/01_数据结构/6. 图/Lecture 20：图基本概念.md"
    },
    {
      "basename": "Lecture 34：定积分的应用",
      "path": "01_数学/01_高等数学/5. 第五章：定积分及反常积分/Lecture 34：定积分的应用.md"
    },
    {
      "basename": "Lecture 31：定积分的基本概念",
      "path": "01_数学/01_高等数学/5. 第五章：定积分及反常积分/Lecture 31：定积分的基本概念.md"
    },
    {
      "basename": "Lecture 27：曲率",
      "path": "01_数学/01_高等数学/3. 第三章：微分中值定理与导数应用/Lecture 27：曲率.md"
    },
    {
      "basename": "Lecture 25：函数的极值与最值",
      "path": "01_数学/01_高等数学/3. 第三章：微分中值定理与导数应用/Lecture 25：函数的极值与最值.md"
    },
    {
      "basename": "Lecture 24：函数的单调性与曲线的凹凸性",
      "path": "01_数学/01_高等数学/3. 第三章：微分中值定理与导数应用/Lecture 24：函数的单调性与曲线的凹凸性.md"
    },
    {
      "basename": "Lecture 23：泰勒公式",
      "path": "01_数学/01_高等数学/3. 第三章：微分中值定理与导数应用/Lecture 23：泰勒公式.md"
    },
    {
      "basename": "Lecture 32：定积分的计算：积分上限的函数",
      "path": "01_数学/01_高等数学/5. 第五章：定积分及反常积分/Lecture 32：定积分的计算：积分上限的函数.md"
    },
    {
      "basename": "Lecture 33：反常积分",
      "path": "01_数学/01_高等数学/5. 第五章：定积分及反常积分/Lecture 33：反常积分.md"
    },
    {
      "basename": "Lecture 23：嵌套结构",
      "path": "02_英语/01_语法/03_长难句分析/Lecture 23：嵌套结构.md"
    },
    {
      "basename": "Lecture 22：分裂结构",
      "path": "02_英语/01_语法/03_长难句分析/Lecture 22：分裂结构.md"
    },
    {
      "basename": "Lecture 18：断开长难句之标点",
      "path": "02_英语/01_语法/03_长难句分析/Lecture 18：断开长难句之标点.md"
    },
    {
      "basename": "Lecture 20：断开长难句之分析主谓",
      "path": "02_英语/01_语法/03_长难句分析/Lecture 20：断开长难句之分析主谓.md"
    },
    {
      "basename": "Lecture 21：简化长难句",
      "path": "02_英语/01_语法/03_长难句分析/Lecture 21：简化长难句.md"
    },
    {
      "basename": "Lecture 18：高阶导数",
      "path": "01_数学/01_高等数学/2. 第二章：导数与微分/Lecture 18：高阶导数.md"
    },
    {
      "basename": "02 导数求导法则",
      "path": "01_数学/04_知识点总结/02 导数求导法则.md"
    },
    {
      "basename": "01 常用求极限方法",
      "path": "01_数学/04_知识点总结/01 常用求极限方法.md"
    },
    {
      "basename": "03 可导、连续、可微之间关系",
      "path": "01_数学/04_知识点总结/03 可导、连续、可微之间关系.md"
    },
    {
      "basename": "05 三角函数计算总结",
      "path": "01_数学/04_知识点总结/05 三角函数计算总结.md"
    },
    {
      "basename": "04 三大中值定理",
      "path": "01_数学/04_知识点总结/04 三大中值定理.md"
    },
    {
      "basename": "Lecture 6：谓语动词的变化 - 考察攻略",
      "path": "02_英语/01_语法/01_简单句/Lecture 6：谓语动词的变化 - 考察攻略.md"
    },
    {
      "basename": "Lecture 9：同位语与插入语",
      "path": "02_英语/01_语法/01_简单句/Lecture 9：同位语与插入语.md"
    },
    {
      "basename": "Lecture 12：名词性从句",
      "path": "02_英语/01_语法/02_长难句/Lecture 12：名词性从句.md"
    },
    {
      "basename": "Lecture 16：倒装句",
      "path": "02_英语/01_语法/02_长难句/Lecture 16：倒装句.md"
    },
    {
      "basename": "Lecture 19：断开长难句之连接词",
      "path": "02_英语/01_语法/03_长难句分析/Lecture 19：断开长难句之连接词.md"
    },
    {
      "basename": "Lecture 1：简单句的核心构成",
      "path": "02_英语/01_语法/01_简单句/Lecture 1：简单句的核心构成.md"
    },
    {
      "basename": "02 长难句_总结",
      "path": "02_英语/01_语法/04_知识点总结/02 长难句_总结.md"
    },
    {
      "basename": "Lecture 15：虚拟语句",
      "path": "02_英语/01_语法/02_长难句/Lecture 15：虚拟语句.md"
    },
    {
      "basename": "Lecture 13：定语从句",
      "path": "02_英语/01_语法/02_长难句/Lecture 13：定语从句.md"
    },
    {
      "basename": "01 简单句_总结",
      "path": "02_英语/01_语法/04_知识点总结/01 简单句_总结.md"
    },
    {
      "basename": "Lecture 21：图的存储及其操作",
      "path": "03_专业/01_数据结构/6. 图/Lecture 21：图的存储及其操作.md"
    },
    {
      "basename": "Lecture 30：分部积分法",
      "path": "01_数学/01_高等数学/4. 第四章：不定积分/Lecture 30：分部积分法.md"
    },
    {
      "basename": "Lecture 29：两类换元积分法",
      "path": "01_数学/01_高等数学/4. 第四章：不定积分/Lecture 29：两类换元积分法.md"
    },
    {
      "basename": "Lecture 28：不定积分",
      "path": "01_数学/01_高等数学/4. 第四章：不定积分/Lecture 28：不定积分.md"
    },
    {
      "basename": "Lecture 3：函数的性质",
      "path": "01_数学/01_高等数学/1. 第一章：函数、极限、连续/Lecture 3：函数的性质.md"
    },
    {
      "basename": "Lecture 2：函数的概念及常见函数",
      "path": "01_数学/01_高等数学/1. 第一章：函数、极限、连续/Lecture 2：函数的概念及常见函数.md"
    },
    {
      "basename": "Lecture 13：磁盘管理",
      "path": "03_专业/02_操作系统/5. 第五章：IO管理/Lecture 13：磁盘管理.md"
    },
    {
      "basename": "Lecture 12：设备独立性软件",
      "path": "03_专业/02_操作系统/5. 第五章：IO管理/Lecture 12：设备独立性软件.md"
    },
    {
      "basename": "Lecture 11：IO管理概述",
      "path": "03_专业/02_操作系统/5. 第五章：IO管理/Lecture 11：IO管理概述.md"
    },
    {
      "basename": "Lecture 10：文件系统",
      "path": "03_专业/02_操作系统/4. 第四章：文件管理/Lecture 10：文件系统.md"
    },
    {
      "basename": "Lecture 8：文件系统基础",
      "path": "03_专业/02_操作系统/4. 第四章：文件管理/Lecture 8：文件系统基础.md"
    },
    {
      "basename": "Lecture 16：导数基本概念",
      "path": "01_数学/01_高等数学/2. 第二章：导数与微分/Lecture 16：导数基本概念.md"
    },
    {
      "basename": "Lecture 17：导数求导法则",
      "path": "01_数学/01_高等数学/2. 第二章：导数与微分/Lecture 17：导数求导法则.md"
    },
    {
      "basename": "Lecture 19：隐函数与参数方程",
      "path": "01_数学/01_高等数学/2. 第二章：导数与微分/Lecture 19：隐函数与参数方程.md"
    },
    {
      "basename": "Lecture 12：函数的连续性",
      "path": "01_数学/01_高等数学/1. 第一章：函数、极限、连续/Lecture 12：函数的连续性.md"
    },
    {
      "basename": "Lecture 15：闭区间上连续函数的性质",
      "path": "01_数学/01_高等数学/1. 第一章：函数、极限、连续/Lecture 15：闭区间上连续函数的性质.md"
    },
    {
      "basename": "Lecture 26：渐近线与函数图形的绘制",
      "path": "01_数学/01_高等数学/3. 第三章：微分中值定理与导数应用/Lecture 26：渐近线与函数图形的绘制.md"
    },
    {
      "basename": "Lecture 23：图的经典应用",
      "path": "03_专业/01_数据结构/6. 图/Lecture 23：图的经典应用.md"
    },
    {
      "basename": "Lecture 6：内存管理概念",
      "path": "03_专业/02_操作系统/3. 第三章：内存管理/Lecture 6：内存管理概念.md"
    }
  ],
  "omittedPaths": [],
  "maxLength": null,
  "openType": "tab"
}